dataExplore/__init__.py
dataExplore/builder.py
dataExplore/dataExplorer.py
dataExplore/director.py
dataExplore/main.py
dataExploreBetter/__init__.py
dataExploreBetter/builder.py
dataExploreBetter/dataExplorer.py
dataExploreBetter/director.py
dataExploreBetter/main.py
dataExploreBetter-0.7.dist-info/LICENSE.txt
dataExploreBetter-0.7.dist-info/METADATA
dataExploreBetter-0.7.dist-info/WHEEL
dataExploreBetter-0.7.dist-info/top_level.txt
dataExploreBetter-0.7.dist-info/RECORD
