Metadata-Version: 2.1
Name: dataExploreBetter
Version: 0.7
Summary: Dataset visualization package
Home-page: https://github.com/alessionuovo/dataExplore
Author: Alessio
Author-email: alex123494@gmail.com
License: UNKNOWN
Platform: UNKNOWN
Classifier: Programming Language :: Python :: 3
Classifier: License :: OSI Approved :: MIT License
Classifier: Operating System :: OS Independent
Requires-Python: >=3.6
